{
	"name": "Pianeta",
	"plugin-id": "Sprite",
	"sid": 291589078804376,
	"isGlobal": false,
	"instanceVariables": [],
	"behaviorTypes": [
		{
			"behaviorId": "MoveTo",
			"name": "MoveTo",
			"sid": 569938449138831
		},
		{
			"behaviorId": "Orbit",
			"name": "Orbit",
			"sid": 545315769023638
		}
	],
	"effectTypes": [],
	"animations": {
		"items": [
			{
				"frames": [
					{
						"width": 111,
						"height": 107,
						"originX": 0.5135135135135135,
						"originY": 0.5046728971962616,
						"originalSource": "",
						"exportFormat": "png",
						"exportQuality": 0.8,
						"imageSpriteId": 6645673,
						"useCollisionPoly": true,
						"duration": 1
					}
				],
				"sid": 574285279657609,
				"name": "Animation 1",
				"isLooping": false,
				"isPingPong": false,
				"repeatCount": 1,
				"repeatTo": 0,
				"speed": 5
			}
		],
		"subfolders": []
	}
}